homegit.py
homegit-0.1.4.dist-info/entry_points.txt
homegit-0.1.4.dist-info/LICENSE
homegit-0.1.4.dist-info/WHEEL
homegit-0.1.4.dist-info/METADATA
homegit-0.1.4.dist-info/RECORD
