Metadata-Version: 2.1
Name: homegit
Version: 0.1.4
Summary: Utility to interact with bare git repos in the home directory.
Author-email: William Klancnik <william@klancnik.com>
Requires-Python: >=3.7
Classifier: Programming Language :: Python :: 3
Classifier: License :: OSI Approved :: MIT License
Classifier: Operating System :: OS Independent
Requires-Dist: requests>2
Project-URL: Bug Tracker, https://github.com/notwillk/homegit/issues
Project-URL: Homepage, https://github.com/notwillk/homegit
